filebutler/Buckets.py
filebutler/CLI.py
filebutler/CLICompleter.py
filebutler/CLIError.py
filebutler/Cache.py
filebutler/CondaEnvCounter.py
filebutler/ConfigError.py
filebutler/Context.py
filebutler/DatasetFilesetCache.py
filebutler/DeletionLog.py
filebutler/FatalError.py
filebutler/Fileset.py
filebutler/FilesetCache.py
filebutler/FilesetInfo.py
filebutler/FilesetInfoAccumulator.py
filebutler/FilesetSelector.py
filebutler/Filespec.py
filebutler/FilespecMerger.py
filebutler/Filter.py
filebutler/FilterFileset.py
filebutler/FindFileset.py
filebutler/GnuFindOutFileset.py
filebutler/Grouper.py
filebutler/Localtime.py
filebutler/MTimeFilter.py
filebutler/Mapper.py
filebutler/Pager.py
filebutler/Pathway.py
filebutler/PercentageProgress.py
filebutler/PooledFile.py
filebutler/SimpleFilesetCache.py
filebutler/SizeFilesetCache.py
filebutler/Sorter.py
filebutler/SymlinkCache.py
filebutler/UnionFileset.py
filebutler/UserFilesetCache.py
filebutler/WeeklyFilesetCache.py
filebutler/__init__.py
filebutler/__main__.py
filebutler/aliases.py
filebutler/options.py
filebutler/util.py
filebutler/version.py
filebutler-0.28.2.dist-info/LICENSE
filebutler-0.28.2.dist-info/METADATA
filebutler-0.28.2.dist-info/WHEEL
filebutler-0.28.2.dist-info/entry_points.txt
filebutler-0.28.2.dist-info/top_level.txt
filebutler-0.28.2.dist-info/RECORD
