Metadata-Version: 2.1
Name: filebutler
Version: 0.28.2
Summary: Utility for managing old files in large directory structures
Home-page: https://github.com/tesujimath/filebutler
Author: Simon Guest
Author-email: simon.guest@tesujimath.org
License: GPLv3
Classifier: Development Status :: 4 - Beta
Classifier: Environment :: Console
Classifier: Intended Audience :: System Administrators
Classifier: License :: OSI Approved :: GNU General Public License v3 (GPLv3)
Classifier: Operating System :: POSIX :: Linux
Classifier: Programming Language :: Python :: 3
Classifier: Topic :: System :: Systems Administration
Classifier: Topic :: Utilities
Requires-Python: >=3.3
License-File: LICENSE
Requires-Dist: pytz
Requires-Dist: setuptools
Requires-Dist: tzlocal
